LICENSE.txt
MANIFEST.in
README.md
README.rst
default_settings.yaml
setup.cfg
setup.py
crowdedText/__init__.py
crowdedText/__version__.py
crowdedText/cl_utils.py
crowdedText/crowdedText.py
crowdedText/setup.cfg
crowdedText/utKit.py
crowdedText.egg-info/PKG-INFO
crowdedText.egg-info/SOURCES.txt
crowdedText.egg-info/dependency_links.txt
crowdedText.egg-info/not-zip-safe
crowdedText.egg-info/requires.txt
crowdedText.egg-info/top_level.txt
crowdedText/commonutils/__init__.py
crowdedText/commonutils/getpackagepath.py
crowdedText/tests/__init__.py