Metadata-Version: 1.1
Name: crowdedText
Version: 0.2.1
Summary: A small library for automatically adjusting text position in matplotlib plots to minimize overlaps (forked and modified from Phlya's adjustText)
Home-page: https://github.com/thespacedoctor/crowdedText
Author: David Young
Author-email: davidrobertyoung@gmail.com
License: MIT
Download-URL: https://github.com/thespacedoctor/crowdedText/archive/v0.2.1.zip
Keywords: matplotlib
Platform: UNKNOWN
Classifier: Development Status :: 4 - Beta
Classifier: License :: OSI Approved :: MIT License
Classifier: Programming Language :: Python :: 2.7
Classifier: Topic :: Utilities
